<?xml version="1.0" encoding="UTF-8"?>
<objects serializationModel="Studio.02.02.00">
	<object class="AudioFile" id="{77299e9f-c2bb-41af-aa1c-7d725b8a1eb7}">
		<property name="assetPath">
			<value>Gunshots/Enemy/TurretProjectile.wav</value>
		</property>
		<property name="frequencyInKHz">
			<value>48</value>
		</property>
		<property name="channelCount">
			<value>2</value>
		</property>
		<property name="length">
			<value>0.47772916666666665</value>
		</property>
		<relationship name="masterAssetFolder">
			<destination>{b55b17b6-2395-4c5d-8c3d-e8a17aa46449}</destination>
		</relationship>
	</object>
</objects>
